tradermade/__init__.py
tradermade/stream.py
tradermade-1.0.dist-info/METADATA
tradermade-1.0.dist-info/WHEEL
tradermade-1.0.dist-info/top_level.txt
tradermade-1.0.dist-info/RECORD
