Metadata-Version: 2.1
Name: tradermade
Version: 1.0
Summary: A package that helps you get Forex data from TraderMade data API
Home-page: https://github.com/tradermade
Author: TraderMade
Author-email: support@tradermade.com
License: MIT
Classifier: Development Status :: 3 - Alpha
Classifier: Intended Audience :: Developers
Classifier: Topic :: Software Development :: Build Tools
Classifier: License :: OSI Approved :: MIT License
Classifier: Programming Language :: Python :: 3.8
Requires-Dist: numpy
Requires-Dist: pandas
Requires-Dist: requests
Requires-Dist: websockets
